tintumon/__init__.py
tintumon/bot.py
tintumon-3.1.1.dist-info/METADATA
tintumon-3.1.1.dist-info/WHEEL
tintumon-3.1.1.dist-info/entry_points.txt
tintumon-3.1.1.dist-info/top_level.txt
tintumon-3.1.1.dist-info/RECORD
